mcp_server/__init__.py
mcp_server/admin.py
mcp_server/apps.py
mcp_server/djangomcp.py
mcp_server/management/commands/mcp_inspect.py
mcp_server/management/commands/stdio_server.py
mcp_server/migrations/__init__.py
mcp_server/models.py
mcp_server/query_tool.py
mcp_server/tests.py
mcp_server/urls.py
mcp_server/views.py
django_mcp_server-0.5.7.dist-info/LICENCE.md
django_mcp_server-0.5.7.dist-info/METADATA
django_mcp_server-0.5.7.dist-info/WHEEL
django_mcp_server-0.5.7.dist-info/RECORD
