Metadata-Version: 2.3
Name: django-mcp-server
Version: 0.5.7
Summary: Django MCP Server is a Django extensions to easily enable AI Agents to interact with Django Apps through the Model Context Protocol it works equally well on WSGI and ASGI
License: MIT
Keywords: django,mcp,model context protocol,tools
Author: Omar BENHAMID
Author-email: omar.benhamid@smart-gts.com
Requires-Python: >=3.10
Classifier: Framework :: Django
Classifier: Framework :: Django :: 4
Classifier: Framework :: Django :: 5
Classifier: Programming Language :: Python :: 3
Classifier: License :: OSI Approved :: MIT License
Requires-Dist: django (>=4.0)
Requires-Dist: djangorestframework (>=3.15.0)
Requires-Dist: inflection (>=0.5.1,<0.6.0)
Requires-Dist: mcp (>=1.8.0)
Requires-Dist: uritemplate (>=4.1.1,<5.0.0)
